{
  "@context": ["http://www.w3.org/ns/csvw"],
  "@type": "TableGroup",
  "dc:title": "Australian Election Study, 2013",
  "dc:description": "The 2013 Australian Election Study (au.edu.anu.ada.ddi.01259) is the tenth in a series of surveys beginning in 1987 that have been timed to coincide with Australian Federal Elections. The series also builds on the 1967, 1969 and 1979 Australian Political Attitudes Surveys. The Australian Election Studies aim to provide a long-term perspective on stability and change in the political attitudes and behaviour of the Australian electorate, and investigate the changing social bases of Australian politics as the economy and society modernise and change character. In addition to these long-term goals, they examine the political issues prevalent in the current election and assess their importance for the election result.",
  "dc:creator": ["Australian Data Archive (ADA)", "The Australian National University"],
  "dc:identifier": "au.edu.anu.ada.ddi.01259",
  "tables": [{
    "url": "aes_2013_01259.csv",
    "tableSchema": {
      "columns": [{
        "name":   "DivisNum",
        "titles": "DivisNum",
        "datatype": "integer"
      }, {
        "name":   "uniqueid",
        "titles": "uniqueid",
        "datatype": "integer"
      }, {
        "titles": "MODE",
        "datatype": {"base": "integer", "minimum": 1, "maximum": 2}
      }, {
        "titles": "DATECOMP"
      }, {
        "titles": "LODGGRP",
        "datatype": {"base": "integer", "minimum": 1, "maximum": 4}
      }, {
        "titles": "State",
        "datatype": {"base": "integer", "minimum": 1, "maximum": 10}
      }, {
        "titles": "Postcode",
        "datatype": {"base": "integer", "minimum": 1, "maximum": 9999}
      }, {
        "name":   "Division",
        "titles": "Division",
        "datatype": "string",
        "lang": "en-AU"
      }, {
        "titles": "Part_Onl", "datatype": "integer"
      }, {
        "titles": "A1"
      }, {
        "titles": "A2"
      }, {
        "titles": "A3P1"
      }, {
        "titles": "A3P2"
      }, {
        "titles": "A3P3"
      }, {
        "titles": "A4"
      }, {
        "titles": "A5P1"
      }, {
        "titles": "A5P6"
      }, {
        "titles": "A5P2"
      }, {
        "titles": "A5P3"
      }, {
        "titles": "A5P4"
      }, {
        "titles": "A5P5"
      }, {
        "titles": "A6"
      }, {
        "titles": "A7"
      }, {
        "titles": "A8P1"
      }, {
        "titles": "A8P2"
      }, {
        "titles": "A8P3"
      }, {
        "titles": "A8P4"
      }, {
        "titles": "A8P5"
      }, {
        "titles": "A8P6"
      }, {
        "titles": "A8P7"
      }, {
        "titles": "A9P1"
      }, {
        "titles": "A9P2"
      }, {
        "titles": "A9P3"
      }, {
        "titles": "A9P4"
      }, {
        "titles": "A9P5"
      }, {
        "titles": "A9P6"
      }, {
        "titles": "A10P1"
      }, {
        "titles": "A10P2"
      }, {
        "titles": "A10P3"
      }, {
        "titles": "A10P4"
      }, {
        "titles": "A10P5"
      }, {
        "titles": "A10P6"
      }, {
        "titles": "A10P7"
      }, {
        "titles": "A11"
      }, {
        "titles": "A12"
      }, {
        "titles": "A13P1"
      }, {
        "titles": "A13P2"
      }, {
        "titles": "A13P3"
      }, {
        "titles": "A13P4"
      }, {
        "titles": "A13P5"
      }, {
        "titles": "A13P6"
      }, {
        "titles": "A14"
      }, {
        "titles": "A15P1"
      }, {
        "titles": "A15P2"
      }, {
        "titles": "A15P3"
      }, {
        "titles": "A15P4"
      }, {
        "titles": "A15P5"
      }, {
        "titles": "A16P1"
      }, {
        "titles": "A16P2"
      }, {
        "titles": "A16P3"
      }, {
        "titles": "A16P4"
      }, {
        "titles": "B1"
      }, {
        "titles": "XB1"
      }, {
        "titles": "B2"
      }, {
        "titles": "B3"
      }, {
        "titles": "B4"
      }, {
        "titles": "B5"
      }, {
        "titles": "B6"
      }, {
        "titles": "B7"
      }, {
        "titles": "B8OWN"
      }, {
        "titles": "B8LIB"
      }, {
        "titles": "B8ALP"
      }, {
        "titles": "B8NAT"
      }, {
        "titles": "B8GRN"
      }, {
        "titles": "B9REPS"
      }, {
        "titles": "XB9REPS"
      }, {
        "titles": "B9SENAT"
      }, {
        "titles": "XB9SENAT"
      }, {
        "titles": "B10REPS"
      }, {
        "titles": "B10SENAT"
      }, {
        "titles": "B11"
      }, {
        "titles": "B12"
      }, {
        "titles": "B13"
      }, {
        "titles": "B14P1"
      }, {
        "titles": "B14P2"
      }, {
        "titles": "B14P3"
      }, {
        "titles": "B14P4"
      }, {
        "titles": "B14P6"
      }, {
        "titles": "B14P7"
      }, {
        "titles": "B14P8"
      }, {
        "titles": "B15"
      }, {
        "titles": "B16"
      }, {
        "titles": "B17LIB"
      }, {
        "titles": "B17ALP"
      }, {
        "titles": "B17NAT"
      }, {
        "titles": "B17GRN"
      }, {
        "titles": "C1RUDD"
      }, {
        "titles": "C1ABBOTT"
      }, {
        "titles": "C1TRUSS"
      }, {
        "titles": "C1JULIA"
      }, {
        "titles": "C1MILNE"
      }, {
        "titles": "C2KRINT"
      }, {
        "titles": "C2KRCMP"
      }, {
        "titles": "C2KRCMPT"
      }, {
        "titles": "C2KRSEN"
      }, {
        "titles": "C2KRLEA"
      }, {
        "titles": "C2KRHON"
      }, {
        "titles": "C2KRKNO"
      }, {
        "titles": "C2KRINS"
      }, {
        "titles": "C2KRTRU"
      }, {
        "titles": "C3TAINT"
      }, {
        "titles": "C3TACMP"
      }, {
        "titles": "C3TACMPT"
      }, {
        "titles": "C3TASEN"
      }, {
        "titles": "C3TALEA"
      }, {
        "titles": "C3TAHON"
      }, {
        "titles": "C3TAKNO"
      }, {
        "titles": "C3TAINS"
      }, {
        "titles": "C3TATRU"
      }, {
        "titles": "C4"
      }, {
        "titles": "C5"
      }, {
        "titles": "C6"
      }, {
        "titles": "C7P6"
      }, {
        "titles": "C7P1"
      }, {
        "titles": "C7P2"
      }, {
        "titles": "C7P3"
      }, {
        "titles": "C7P4"
      }, {
        "titles": "C7P5"
      }, {
        "titles": "C8"
      }, {
        "titles": "C9"
      }, {
        "titles": "C10"
      }, {
        "titles": "D1TAX"
      }, {
        "titles": "D1IMMIG"
      }, {
        "titles": "D1EDUC"
      }, {
        "titles": "D1ENVIR"
      }, {
        "titles": "D1INDREL"
      }, {
        "titles": "D1HEALTH"
      }, {
        "titles": "D1REAS"
      }, {
        "titles": "D1GLOBAL"
      }, {
        "titles": "D1CARBON"
      }, {
        "titles": "D1ECONO"
      }, {
        "titles": "D2TAX"
      }, {
        "titles": "D2IMMIG"
      }, {
        "titles": "D2EDUC"
      }, {
        "titles": "D2ENVIR"
      }, {
        "titles": "D2INDREL"
      }, {
        "titles": "D2HEALTH"
      }, {
        "titles": "D2REAS"
      }, {
        "titles": "D2GLOBAL"
      }, {
        "titles": "D2CARBON"
      }, {
        "titles": "D2ECONO"
      }, {
        "titles": "D3P1"
      }, {
        "titles": "D3P2"
      }, {
        "titles": "D4HHOLD"
      }, {
        "titles": "D4CNTRY"
      }, {
        "titles": "D5HHOLD"
      }, {
        "titles": "D5CNTRY"
      }, {
        "titles": "D6HHOLD"
      }, {
        "titles": "D6CNTRY"
      }, {
        "titles": "D7HHOLD"
      }, {
        "titles": "D7CNTRY"
      }, {
        "titles": "D8P1"
      }, {
        "titles": "D8P2"
      }, {
        "titles": "D8P3"
      }, {
        "titles": "D8P4"
      }, {
        "titles": "D8P5"
      }, {
        "titles": "D8P6"
      }, {
        "titles": "D8P7"
      }, {
        "titles": "D8P8"
      }, {
        "titles": "D9"
      }, {
        "titles": "D10"
      }, {
        "titles": "D11"
      }, {
        "titles": "D12P1"
      }, {
        "titles": "D12P2"
      }, {
        "titles": "D13P1"
      }, {
        "titles": "D13P2"
      }, {
        "titles": "D13P3"
      }, {
        "titles": "D13P4"
      }, {
        "titles": "D13P5"
      }, {
        "titles": "D13P6"
      }, {
        "titles": "E1"
      }, {
        "titles": "E2MIGEO"
      }, {
        "titles": "E2NUDSEX"
      }, {
        "titles": "E2ABLAND"
      }, {
        "titles": "E2EQUOP"
      }, {
        "titles": "E2IMMIG"
      }, {
        "titles": "E2ABOR"
      }, {
        "titles": "E2ASIA"
      }, {
        "titles": "E3"
      }, {
        "titles": "E4"
      }, {
        "titles": "E5P1"
      }, {
        "titles": "E5P2"
      }, {
        "titles": "E5P3"
      }, {
        "titles": "E5P4"
      }, {
        "titles": "E6DEATHP"
      }, {
        "titles": "E6MARIJ"
      }, {
        "titles": "E6LAWBRK"
      }, {
        "titles": "E6PREF"
      }, {
        "titles": "E6BOATS"
      }, {
        "titles": "E6SAME"
      }, {
        "titles": "E6WHITE"
      }, {
        "titles": "E6ETHNIC"
      }, {
        "titles": "E6OPP"
      }, {
        "titles": "E7P1"
      }, {
        "titles": "E7P2"
      }, {
        "titles": "E8"
      }, {
        "titles": "E9"
      }, {
        "titles": "F1"
      }, {
        "titles": "F2"
      }, {
        "titles": "F3"
      }, {
        "titles": "F4"
      }, {
        "titles": "F5JAPAN"
      }, {
        "titles": "F5US"
      }, {
        "titles": "F5CHINA"
      }, {
        "titles": "F5VIETN"
      }, {
        "titles": "F5MALAY"
      }, {
        "titles": "F5INDON"
      }, {
        "titles": "F6P1"
      }, {
        "titles": "F6P4"
      }, {
        "titles": "F6P7"
      }, {
        "titles": "F6P8"
      }, {
        "titles": "F7"
      }, {
        "titles": "F8P1"
      }, {
        "titles": "F8P2"
      }, {
        "titles": "F8P3"
      }, {
        "titles": "F8P4"
      }, {
        "titles": "F9"
      }, {
        "titles": "F10"
      }, {
        "titles": "F11"
      }, {
        "titles": "F12"
      }, {
        "titles": "F13"
      }, {
        "titles": "F14NAMER"
      }, {
        "titles": "F14PARTR"
      }, {
        "titles": "F14PARTY"
      }, {
        "titles": "F15"
      }, {
        "titles": "F16P1"
      }, {
        "titles": "F16P2"
      }, {
        "titles": "F16P3"
      }, {
        "titles": "F16P4"
      }, {
        "titles": "F16P5"
      }, {
        "titles": "F16P6"
      }, {
        "titles": "G1"
      }, {
        "titles": "G1age"
      }, {
        "titles": "G2"
      }, {
        "titles": "G3"
      }, {
        "titles": "G4"
      }, {
        "titles": "G5"
      }, {
        "titles": "XG5"
      }, {
        "titles": "G5POS"
      }, {
        "titles": "G5EMPLOY"
      }, {
        "titles": "G5SUPERV"
      }, {
        "titles": "G6"
      }, {
        "titles": "H1"
      }, {
        "titles": "H2"
      }, {
        "titles": "Age"
      }, {
        "titles": "Ageder"
      }, {
        "titles": "H3"
      }, {
        "titles": "H4P1"
      }, {
        "titles": "H4P2"
      }, {
        "titles": "H4P3"
      }, {
        "titles": "H4P4"
      }, {
        "titles": "H5DAD"
      }, {
        "titles": "H5MUM"
      }, {
        "titles": "H6"
      }, {
        "titles": "XH6"
      }, {
        "titles": "H7"
      }, {
        "titles": "H8"
      }, {
        "titles": "H9"
      }, {
        "titles": "H10"
      }, {
        "titles": "H11"
      }, {
        "titles": "H12ATTCH"
      }, {
        "titles": "H12MLMED"
      }, {
        "titles": "H12WPBLG"
      }, {
        "titles": "H12DWLD"
      }, {
        "titles": "H13"
      }, {
        "titles": "H14"
      }, {
        "titles": "H15"
      }, {
        "titles": "H16"
      }, {
        "titles": "H17"
      }, {
        "titles": "H18"
      }, {
        "titles": "XH18"
      }, {
        "titles": "H19"
      }, {
        "titles": "H20"
      }, {
        "titles": "H21"
      }, {
        "titles": "H22"
      }, {
        "titles": "XH22"
      }, {
        "titles": "H23OWN"
      }, {
        "titles": "XH23OWN"
      }, {
        "titles": "H23MUM"
      }, {
        "titles": "XH23MUM"
      }, {
        "titles": "H23DAD"
      }, {
        "titles": "XH23DAD"
      }, {
        "titles": "H24OWN"
      }, {
        "titles": "H24MUM"
      }, {
        "titles": "H24DAD"
      }, {
        "titles": "H25P1"
      }, {
        "titles": "H25P2"
      }, {
        "titles": "H25P3"
      }, {
        "titles": "H25P4"
      }, {
        "titles": "H25P5"
      }, {
        "titles": "H25P6"
      }, {
        "titles": "H25P7"
      }, {
        "titles": "H25P8"
      }, {
        "titles": "H25P9"
      }, {
        "titles": "H25P10"
      }, {
        "titles": "H25P11"
      }, {
        "titles": "H25P12"
      }, {
        "titles": "H25P13"
      }, {
        "titles": "H25P14"
      }, {
        "titles": "h26you_1"
      }, {
        "titles": "h26you_2"
      }, {
        "titles": "h26mum_1"
      }, {
        "titles": "h26mum_2"
      }, {
        "titles": "h26dad_1"
      }, {
        "titles": "h26dad_2"
      }, {
        "titles": "H27"
      }, {
        "titles": "H28"
      }, {
        "titles": "H29"
      }, {
        "titles": "H30"
      }, {
        "titles": "H31"
      }, {
        "titles": "weight"
      }, {
        "titles": "StateMap"
      }, {
        "titles": "ALP_1PRF"
      }, {
        "titles": "LP_1PRF"
      }, {
        "titles": "LNP_1PRF"
      }, {
        "titles": "NP_1PRF"
      }, {
        "titles": "CLP_1PRF"
      }, {
        "titles": "OTH_1PRF"
      }, {
        "titles": "ALP_2PP"
      }, {
        "titles": "LNC_2PP"
      }, {
        "titles": "STATEAB"
      }, {
        "titles": "ENROLMNT"
      }, {
        "titles": "TURNOUT"
      }, {
        "titles": "TURNPCT"
      }, {
        "titles": "TURNSWG"
      }, {
        "titles": "ORDVOTES"
      }, {
        "titles": "ABSVOTES"
      }, {
        "titles": "PRVVOTES"
      }, {
        "titles": "PREVOTES"
      }, {
        "titles": "POSVOTES"
      }, {
        "titles": "TOTVOTES"
      }, {
        "titles": "TOTPCT"
      }, {
        "titles": "FORVOTES"
      }, {
        "titles": "INFVOTES"
      }, {
        "titles": "INFPCT"
      }, {
        "titles": "INFSWING"
      }, {
        "titles": "CANDIDN"
      }, {
        "titles": "PARTYABN"
      }, {
        "titles": "TOTVOTN"
      }, {
        "titles": "SWINGN"
      }, {
        "titles": "CANDIDY"
      }, {
        "titles": "PARTYABY"
      }, {
        "titles": "TOTVOTY"
      }, {
        "titles": "SWINGY"
      }],
      "aboutUrl": "http://example.org/records/{#uniqueid}",
      "propertyUrl": "http://example.org/ns/{_name}",
      "primaryKey": "uniqueid",
      "foreignKeys": [{
        "columnReference": "DivisNum",
        "reference": {
          "resource": "aes_divs.csv",
          "columnReference": "DivisNum"
        }
      }, {
        "columnReference": "Division",
        "reference": {
          "resource": "aes_divs.csv",
          "columnReference": "Division"
        }
      }]
    }
  }, {
    "url": "aes_divs.csv",
    "suppressOutput": true,
    "tableSchema": {
      "columns": [{
        "name":   "DivisNum",
        "titles": "DivisNum",
        "datatype": "integer"
      }, {
        "name":   "Division",
        "titles": "Division",
        "datatype": "string",
        "lang": "en-AU"
      }],
      "primaryKey": "DivisNum"
    }
  }]
}
